torch_circuit/__init__.py
torch_circuit/circuit.py
torch_circuit-0.9.1.dist-info/licenses/LICENSE
torch_circuit-0.9.1.dist-info/METADATA
torch_circuit-0.9.1.dist-info/WHEEL
torch_circuit-0.9.1.dist-info/top_level.txt
torch_circuit-0.9.1.dist-info/RECORD
