Metadata-Version: 2.4
Name: torch-circuit
Version: 0.9.1
Summary: A PyTorch extension for easy skip connections and repeatable blocks
Home-page: https://github.com/your-username/torch-circuit
Author: ntippens
Author-email: ntippens <ndtippens@gmail.com>
Maintainer-email: ntippens <ndtippens@gmail.com>
License: MIT
Project-URL: Homepage, https://github.com/ndtippens/
Project-URL: Repository, https://github.com/ndtippens/torch-circuit
Project-URL: Documentation, https://github.com/ndtippens/torch-circuit#readme
Project-URL: Bug Reports, https://github.com/ndtippens/torch-circuit/issues
Keywords: pytorch,neural-networks,deep-learning,skip-connections
Classifier: Development Status :: 3 - Alpha
Classifier: Intended Audience :: Developers
Classifier: Intended Audience :: Science/Research
Classifier: Operating System :: OS Independent
Classifier: Programming Language :: Python :: 3
Classifier: Programming Language :: Python :: 3.8
Classifier: Programming Language :: Python :: 3.9
Classifier: Programming Language :: Python :: 3.10
Classifier: Programming Language :: Python :: 3.11
Classifier: Programming Language :: Python :: 3.12
Classifier: Topic :: Scientific/Engineering :: Artificial Intelligence
Classifier: Topic :: Software Development :: Libraries :: Python Modules
Requires-Python: >=3.8
License-File: LICENSE
Requires-Dist: torch>=1.9.0
Requires-Dist: torchvision>=0.10.0
Requires-Dist: matplotlib>=3.3.0
Requires-Dist: numpy>=1.19.0
Provides-Extra: dev
Requires-Dist: pytest>=6.0; extra == "dev"
Requires-Dist: pytest-cov>=2.0; extra == "dev"
Requires-Dist: black>=21.0; extra == "dev"
Requires-Dist: flake8>=3.8; extra == "dev"
Requires-Dist: mypy>=0.800; extra == "dev"
Provides-Extra: examples
Requires-Dist: jupyter>=1.0.0; extra == "examples"
Requires-Dist: notebook>=6.0.0; extra == "examples"
Dynamic: author
Dynamic: home-page
Dynamic: license-file
Dynamic: requires-python
